README.md
setup.py
poi4py/__init__.py
poi4py.egg-info/PKG-INFO
poi4py.egg-info/SOURCES.txt
poi4py.egg-info/dependency_links.txt
poi4py.egg-info/requires.txt
poi4py.egg-info/top_level.txt
poi4py/java/lib
poi4py/java/ooxml-lib
poi4py/java/poi-3.17.jar
poi4py/java/poi-excelant-3.17.jar
poi4py/java/poi-ooxml-3.17.jar
poi4py/java/poi-ooxml-schemas-3.17.jar
poi4py/java/poi-scratchpad-3.17.jar
tests/__init__.py
tests/test_excel.py