Metadata-Version: 1.1
Name: poi4py
Version: 0.0.8
Summary: Apache POI wrapper for better access of MS Office files
Home-page: https://github.com/youngrok/poi4py
Author: Youngrok Pak
Author-email: pak.youngrok@gmail.com
License: UNKNOWN
Keywords: excel word powerpoint poi java
Platform: UNKNOWN
Classifier: Development Status :: 3 - Alpha
Classifier: Topic :: System :: Installation/Setup
Classifier: License :: OSI Approved :: BSD License
